torchlure/__init__.py
torchlure/noise_schedulers.py
torchlure/optim.py
torchlure/utils.py
torchlure/datasets/__init__.py
torchlure/datasets/d4rl/__init__.py
torchlure/datasets/d4rl/d4rl_infos.py
torchlure/datasets/offline_rl/__init__.py
torchlure/datasets/offline_rl/minari_ext.py
torchlure/functional/__init__.py
torchlure/functions/__init__.py
torchlure/networks/__init__.py
torchlure/networks/chebykan.py
torchlure/networks/relukan.py
torchlure-0.2409.7.dist-info/METADATA
torchlure-0.2409.7.dist-info/WHEEL
torchlure-0.2409.7.dist-info/top_level.txt
torchlure-0.2409.7.dist-info/RECORD
