Metadata-Version: 2.1
Name: torchlure
Version: 0.2409.7
Author-email: fuyutarow <fuyutarow@gmail.com>
Project-URL: Homepage, https://github.com/fuyutarow/torchlure
Project-URL: Repository, https://github.com/fuyutarow/torchlure
Keywords: pytorch
Requires-Python: >=3.8
Requires-Dist: torch>=2.1
Requires-Dist: sophia-opt>=0.2.2
Requires-Dist: gymnasium>=0.29.1
Requires-Dist: gdown>=5.2.0
Requires-Dist: h5py>=3.11.0
Requires-Dist: einops>=0.8.0
Requires-Dist: torchtyping>=0.1.4
Requires-Dist: minari>=0.4.3
Requires-Dist: tensordict>=0.1.2
Requires-Dist: tqdm>=4.66.4
Requires-Dist: jaxtyping>=0.2.19
Provides-Extra: rl
